README.rst
setup.py
pagerank/__init__.py
pagerank/pranker.py
pagerank.egg-info/PKG-INFO
pagerank.egg-info/SOURCES.txt
pagerank.egg-info/dependency_links.txt
pagerank.egg-info/requires.txt
pagerank.egg-info/top_level.txt
pagerank/lib/__init__.py
pagerank/lib/xgoogle/__init__.py
pagerank/lib/xgoogle/browser.py
pagerank/lib/xgoogle/googlesets.py
pagerank/lib/xgoogle/search.py
pagerank/lib/xgoogle/sponsoredlinks.py
pagerank/lib/xgoogle/translate.py