Metadata-Version: 1.0
Name: pagerank
Version: 0.1.1
Summary: Utility to get pagerank of keywords on google
Home-page: http://daniyalzade.com
Author: Eytan Daniyalzade
Author-email: eytan85@gmail.com
License: UNKNOWN
Platform: UNKNOWN
